{
  "users": [
    {
      "name": "admin",
      "email": "admin@gmail.com",
      "password": "admin",
      "tipo": "admin",
      "id": "zihmjB8"
    },
    {
      "id": "528b",
      "name": "alina",
      "email": "alina@gmail.com",
      "password": "123",
      "tipo": "user"
    },
    {
      "id": "2cb9",
      "name": "pepa",
      "email": "pepa@gmail.com",
      "password": "123",
      "tipo": "user"
    },
    {
      "id": "d3cf",
      "name": "maria",
      "email": "m@gmail.com",
      "password": "123",
      "tipo": "user"
    },
    {
      "name": "maria",
      "email": "54thfg@hfghgf.fh",
      "password": "1234",
      "tipo": "usuario",
      "id": "8nnBF4O"
    }
  ],
  "productos": [
    {
      "nombre": "Tortuga",
      "precio": "13",
      "imagen": "1740559186229-tortuga.webp",
      "id": 1740559187112
    },
    {
      "nombre": "Ajolote",
      "precio": "14",
      "imagen": "1740559205315-ajolote.jpg",
      "id": 1740559213451
    },
    {
      "nombre": "Camello",
      "precio": "9",
      "imagen": "1740559292411-d.webp",
      "id": 1740559293225
    },
    {
      "nombre": "Fideos",
      "precio": "12",
      "imagen": "1740559314613-fideos.webp",
      "id": 1740559322395
    },
    {
      "nombre": "Papper",
      "precio": "13",
      "imagen": "1740569634527-paper.webp",
      "id": 1740569659652
    },
    {
      "nombre": "Macarrones",
      "precio": "12",
      "imagen": "1740642981042-macarrones.webp",
      "id": 1740642983590
    },
    {
      "nombre": "Pear",
      "precio": "9",
      "imagen": "1740642995141-pear.webp",
      "id": 1740642996093
    }
  ]
}